design.sv
// Code your design here
module pc(
    input clk,
    input reset,
    input [31:0] next_pc,
    output reg [31:0] pc_out
);

always @(posedge clk or posedge reset)
begin
    if(reset)
        pc_out <= 32'd0;
    else
        pc_out <= next_pc;
end

endmodule

//Instruction Memory
module instruction_memory(
    input [31:0] address,
    output [31:0] instruction
);

reg [31:0] memory [0:255];

initial begin
    memory[0] = 32'h00221820; // ADD
    memory[1] = 32'h00632022; // SUB
    memory[2] = 32'h00852824; // AND
    memory[3] = 32'h00A63025; // OR
end

assign instruction = memory[address[9:2]];

endmodule

//Register File
module register_file(
    input clk,
    input reg_write,
    input [4:0] rs,
    input [4:0] rt,
    input [4:0] rd,
    input [31:0] write_data,
    output [31:0] read_data1,
    output [31:0] read_data2
);

reg [31:0] reg_mem [0:31];

assign read_data1 = reg_mem[rs];
assign read_data2 = reg_mem[rt];

always @(posedge clk)
begin
    if(reg_write)
        reg_mem[rd] <= write_data;
end

endmodule

//ALU
module alu(
    input [31:0] a,
    input [31:0] b,
    input [2:0] alu_control,
    output reg [31:0] result,
    output zero
);

always @(*)
begin
    case(alu_control)
        3'b000: result = a + b;
        3'b001: result = a - b;
        3'b010: result = a & b;
        3'b011: result = a | b;
        3'b100: result = (a < b);
        default: result = 32'd0;
    endcase
end

assign zero = (result == 0);

endmodule

//Data Memory
module data_memory(
    input clk,
    input mem_read,
    input mem_write,
    input [31:0] address,
    input [31:0] write_data,
    output reg [31:0] read_data
);

reg [31:0] mem [0:255];

always @(posedge clk)
begin
    if(mem_write)
        mem[address[9:2]] <= write_data;
end

always @(*)
begin
    if(mem_read)
        read_data = mem[address[9:2]];
    else
        read_data = 32'd0;
end

endmodule

//Control Unit
module control_unit(
    input [5:0] opcode,

    output reg reg_write,
    output reg mem_read,
    output reg mem_write,
    output reg mem_to_reg,
    output reg alu_src
);

always @(*)
begin
    case(opcode)

        6'b000000:
        begin
            reg_write = 1;
            mem_read = 0;
            mem_write = 0;
            mem_to_reg = 0;
            alu_src = 0;
        end

        6'b100011:
        begin
            reg_write = 1;
            mem_read = 1;
            mem_write = 0;
            mem_to_reg = 1;
            alu_src = 1;
        end

        6'b101011:
        begin
            reg_write = 0;
            mem_read = 0;
            mem_write = 1;
            mem_to_reg = 0;
            alu_src = 1;
        end

        default:
        begin
            reg_write = 0;
            mem_read = 0;
            mem_write = 0;
            mem_to_reg = 0;
            alu_src = 0;
        end
    endcase
end

endmodule

//IF/ID Pipeline Register
module if_id(
    input clk,
    input reset,

    input [31:0] pc_in,
    input [31:0] instr_in,

    output reg [31:0] pc_out,
    output reg [31:0] instr_out
);

always @(posedge clk or posedge reset)
begin
    if(reset)
    begin
        pc_out <= 0;
        instr_out <= 0;
    end
    else
    begin
        pc_out <= pc_in;
        instr_out <= instr_in;
    end
end

endmodule

//ID/EX Pipeline Register
module id_ex(
    input clk,
    input reset,

    input [31:0] a_in,
    input [31:0] b_in,

    output reg [31:0] a_out,
    output reg [31:0] b_out
);

always @(posedge clk or posedge reset)
begin
    if(reset)
    begin
        a_out <= 0;
        b_out <= 0;
    end
    else
    begin
        a_out <= a_in;
        b_out <= b_in;
    end
end

endmodule

//EX/MEM Pipeline Register
module ex_mem(
    input clk,
    input reset,

    input [31:0] alu_in,
    output reg [31:0] alu_out
);

always @(posedge clk or posedge reset)
begin
    if(reset)
        alu_out <= 0;
    else
        alu_out <= alu_in;
end

endmodule

//MEM/WB Pipeline Register
module mem_wb(
    input clk,
    input reset,

    input [31:0] data_in,
    output reg [31:0] data_out
);

always @(posedge clk or posedge reset)
begin
    if(reset)
        data_out <= 0;
    else
        data_out <= data_in;
end

endmodule

//Forwarding Unit
module forwarding_unit(
    input [4:0] ex_rs,
    input [4:0] ex_rt,
    input [4:0] mem_rd,
    input [4:0] wb_rd,
    input mem_regwrite,
    input wb_regwrite,

    output reg [1:0] forwardA,
    output reg [1:0] forwardB
);

always @(*)
begin
    forwardA = 2'b00;
    forwardB = 2'b00;

    if(mem_regwrite && (mem_rd == ex_rs))
        forwardA = 2'b10;

    if(mem_regwrite && (mem_rd == ex_rt))
        forwardB = 2'b10;

    if(wb_regwrite && (wb_rd == ex_rs))
        forwardA = 2'b01;

    if(wb_regwrite && (wb_rd == ex_rt))
        forwardB = 2'b01;
end

endmodule

//Hazard Detection Unit
module hazard_detection(
    input id_ex_memread,
    input [4:0] id_ex_rt,
    input [4:0] if_id_rs,
    input [4:0] if_id_rt,

    output reg stall
);

always @(*)
begin
    if(id_ex_memread &&
      ((id_ex_rt == if_id_rs) ||
       (id_ex_rt == if_id_rt)))
        stall = 1;
    else
        stall = 0;
end

endmodule

//Top Module Skeleton
module processor_top(
    input clk,
    input reset
);

wire [31:0] pc_current;
wire [31:0] next_pc;
wire [31:0] instruction;

assign next_pc = pc_current + 4;

pc PC(
    .clk(clk),
    .reset(reset),
    .next_pc(next_pc),
    .pc_out(pc_current)
);

instruction_memory IM(
    .address(pc_current),
    .instruction(instruction)
);

endmodule

testbench.sv
// Code your testbench here
// or browse Examples
module tb_processor;

reg clk;
reg reset;

processor_top DUT(
    .clk(clk),
    .reset(reset)
);

always #5 clk = ~clk;

initial
begin
    clk = 0;
    reset = 1;

    #20;
    reset = 0;

    #300;
    $finish;
end

initial
begin
    $dumpfile("pipeline.vcd");
    $dumpvars(0,tb_processor);
end

endmodule

pipeline.vcd
$date
	Mon Jun  1 05:33:45 2026
$end

$version
	Synopsys VCS version X-2025.06-SP1_Full64
$end

$timescale
	1ns
$end

$comment Csum: 1 f43ea06d46988968 $end


$scope module tb_processor $end
$var reg 1 ! clk $end
$var reg 1 " reset $end

$scope module DUT $end
$var wire 1 ! clk $end
$var wire 1 " reset $end
$var wire 32 # pc_current [31:0] $end
$var wire 32 $ next_pc [31:0] $end
$var wire 32 % instruction [31:0] $end

$scope module PC $end
$var wire 1 ! clk $end
$var wire 1 " reset $end
$var wire 32 $ next_pc [31:0] $end
$var reg 32 # pc_out [31:0] $end
$upscope $end


$scope module IM $end
$var wire 32 # address [31:0] $end
$var wire 32 % instruction [31:0] $end
$upscope $end

$upscope $end

$upscope $end

$enddefinitions $end

#0
$dumpvars
0!
1"
b00000000001000100001100000100000 %
b00000000000000000000000000000100 $
b00000000000000000000000000000000 #
$end
#5
1!
#10
0!
#15
1!
#20
0"
0!
#25
1!
b00000000000000000000000000000100 #
b00000000000000000000000000001000 $
b00000000011000110010000000100010 %
#30
0!
#35
1!
b00000000000000000000000000001000 #
b00000000000000000000000000001100 $
b00000000100001010010100000100100 %
#40
0!
#45
1!
b00000000000000000000000000001100 #
b00000000000000000000000000010000 $
b00000000101001100011000000100101 %
#50
0!
#55
1!
b00000000000000000000000000010000 #
b00000000000000000000000000010100 $
bxxxxxxxxxxxxxxxxxxxxxxxxxxxxxxxx %
#60
0!
#65
1!
b00000000000000000000000000010100 #
b00000000000000000000000000011000 $
#70
0!
#75
1!
b00000000000000000000000000011000 #
b00000000000000000000000000011100 $
#80
0!
#85
1!
b00000000000000000000000000011100 #
b00000000000000000000000000100000 $
#90
0!
#95
1!
b00000000000000000000000000100000 #
b00000000000000000000000000100100 $
#100
0!
#105
1!
b00000000000000000000000000100100 #
b00000000000000000000000000101000 $
#110
0!
#115
1!
b00000000000000000000000000101000 #
b00000000000000000000000000101100 $
#120
0!
#125
1!
b00000000000000000000000000101100 #
b00000000000000000000000000110000 $
#130
0!
#135
1!
b00000000000000000000000000110000 #
b00000000000000000000000000110100 $
#140
0!
#145
1!
b00000000000000000000000000110100 #
b00000000000000000000000000111000 $
#150
0!
#155
1!
b00000000000000000000000000111000 #
b00000000000000000000000000111100 $
#160
0!
#165
1!
b00000000000000000000000000111100 #
b00000000000000000000000001000000 $
#170
0!
#175
1!
b00000000000000000000000001000000 #
b00000000000000000000000001000100 $
#180
0!
#185
1!
b00000000000000000000000001000100 #
b00000000000000000000000001001000 $
#190
0!
#195
1!
b00000000000000000000000001001000 #
b00000000000000000000000001001100 $
#200
0!
#205
1!
b00000000000000000000000001001100 #
b00000000000000000000000001010000 $
#210
0!
#215
1!
b00000000000000000000000001010000 #
b00000000000000000000000001010100 $
#220
0!
#225
1!
b00000000000000000000000001010100 #
b00000000000000000000000001011000 $
#230
0!
#235
1!
b00000000000000000000000001011000 #
b00000000000000000000000001011100 $
#240
0!
#245
1!
b00000000000000000000000001011100 #
b00000000000000000000000001100000 $
#250
0!
#255
1!
b00000000000000000000000001100000 #
b00000000000000000000000001100100 $
#260
0!
#265
1!
b00000000000000000000000001100100 #
b00000000000000000000000001101000 $
#270
0!
#275
1!
b00000000000000000000000001101000 #
b00000000000000000000000001101100 $
#280
0!
#285
1!
b00000000000000000000000001101100 #
b00000000000000000000000001110000 $
#290
0!
#295
1!
b00000000000000000000000001110000 #
b00000000000000000000000001110100 $
#300
0!
#305
1!
b00000000000000000000000001110100 #
b00000000000000000000000001111000 $
#310
0!
#315
1!
b00000000000000000000000001111000 #
b00000000000000000000000001111100 $
